ztest_tejas360/__init__.py
ztest_tejas360/tejas.py
ztest_tejas360-0.1.dist-info/LICENSE
ztest_tejas360-0.1.dist-info/WHEEL
ztest_tejas360-0.1.dist-info/METADATA
ztest_tejas360-0.1.dist-info/RECORD
