Metadata-Version: 2.1
Name: ztest_tejas360
Version: 0.1
Summary: A package
Author-email: tejas <tejas9patil@gmail.com>
Classifier: License :: OSI Approved :: MIT License
